LICENSE
README.txt
setup.cfg
setup.py
tinymce_2_0_5_1.tgz
TurboTinyMCE.egg-info/PKG-INFO
TurboTinyMCE.egg-info/SOURCES.txt
TurboTinyMCE.egg-info/dependency_links.txt
TurboTinyMCE.egg-info/entry_points.txt
TurboTinyMCE.egg-info/not-zip-safe
TurboTinyMCE.egg-info/requires.txt
TurboTinyMCE.egg-info/top_level.txt
tinymce/__init__.py
tinymce/release.py
tinymce/widgets.py
tinymce/static/javascript/blank.htm
tinymce/static/javascript/license.txt
tinymce/static/javascript/tiny_mce.js
tinymce/static/javascript/tiny_mce_popup.js
tinymce/static/javascript/tiny_mce_src.js
tinymce/static/javascript/langs/en.js
tinymce/static/javascript/langs/es.js
tinymce/static/javascript/langs/readme.txt
tinymce/static/javascript/plugins/readme.txt
tinymce/static/javascript/plugins/_template/editor_plugin.js
tinymce/static/javascript/plugins/_template/editor_plugin_src.js
tinymce/static/javascript/plugins/_template/popup.htm
tinymce/static/javascript/plugins/_template/readme.txt
tinymce/static/javascript/plugins/_template/images/template.gif
tinymce/static/javascript/plugins/_template/langs/en.js
tinymce/static/javascript/plugins/advhr/editor_plugin.js
tinymce/static/javascript/plugins/advhr/editor_plugin_src.js
tinymce/static/javascript/plugins/advhr/readme.txt
tinymce/static/javascript/plugins/advhr/rule.htm
tinymce/static/javascript/plugins/advhr/css/advhr.css
tinymce/static/javascript/plugins/advhr/images/advhr.gif
tinymce/static/javascript/plugins/advhr/jscripts/rule.js
tinymce/static/javascript/plugins/advhr/langs/en.js
tinymce/static/javascript/plugins/advimage/editor_plugin.js
tinymce/static/javascript/plugins/advimage/editor_plugin_src.js
tinymce/static/javascript/plugins/advimage/image.htm
tinymce/static/javascript/plugins/advimage/readme.txt
tinymce/static/javascript/plugins/advimage/css/advimage.css
tinymce/static/javascript/plugins/advimage/images/sample.gif
tinymce/static/javascript/plugins/advimage/jscripts/functions.js
tinymce/static/javascript/plugins/advimage/langs/en.js
tinymce/static/javascript/plugins/advlink/editor_plugin.js
tinymce/static/javascript/plugins/advlink/editor_plugin_src.js
tinymce/static/javascript/plugins/advlink/link.htm
tinymce/static/javascript/plugins/advlink/readme.txt
