Metadata-Version: 1.0
Name: TurboTinyMCE
Version: 1.0.3
Summary: TinyMCE widget for TurboGears
Home-page: http://www.turbogears.org/svn/turbogears/widgets/TurboTinyMCE
Author: Alberto Valverde Gonzalez
Author-email: alberto@toscat.net
License: LGPL
Download-URL: http://www.turbogears.org/svn/turbogears/widgets/TurboTinyMCE
Keywords: turbogears.widgets
Platform: UNKNOWN
Classifier: Development Status :: 3 - Alpha
Classifier: Operating System :: OS Independent
Classifier: Programming Language :: Python
Classifier: Topic :: Software Development :: Libraries :: Python Modules
Classifier: Framework :: TurboGears
Classifier: Framework :: TurboGears :: Widgets
